scscope/__init__.py
scscope/large_scale_processing.py
scscope/ops.py
scScope_cpu-0.1.5.dist-info/LICENSE
scScope_cpu-0.1.5.dist-info/METADATA
scScope_cpu-0.1.5.dist-info/WHEEL
scScope_cpu-0.1.5.dist-info/top_level.txt
scScope_cpu-0.1.5.dist-info/RECORD
