Metadata-Version: 1.0
Name: scScope_cpu
Version: 0.1.5
Summary: scScope is a deep-learning based approach for single cell RNA-seq analysis. 
Home-page: https://github.com/AltschulerWu-Lab/scScope
Author: ['Yue Deng', 'Feng Bao']
Author-email: yue.deng@ucsf.edu
License: Apache License 2.0
Platform: UNKNOWN
